pypnm/__init__.py
pypnm/pnmlpnm.py
pypnm-2.21.3.4.post5.dist-info/licenses/LICENSE
pypnm-2.21.3.4.post5.dist-info/METADATA
pypnm-2.21.3.4.post5.dist-info/WHEEL
pypnm-2.21.3.4.post5.dist-info/top_level.txt
pypnm-2.21.3.4.post5.dist-info/RECORD
