Metadata-Version: 2.4
Name: PyPNM
Version: 2.21.3.4.post5
Summary: Reading, displaying and writing PNM image files, including 16 bits per channel, in pure Python
Home-page: https://dnyarri.github.io/
Author: Ilya Razmanov
Author-email: ilyarazmanov@gmail.com
Project-URL: Source, https://github.com/Dnyarri/PyPNM
Project-URL: Documentation, https://dnyarri.github.io/pypnm/pypnm.pdf
Project-URL: Changelog, https://github.com/Dnyarri/PyPNM/blob/py34/CHANGELOG.md
Project-URL: Issues, https://github.com/Dnyarri/PyPNM/issues
Keywords: ppm,pgm,pbm,pnm,Netpbm,image,bitmap,greyscale,RGB,format,python
Classifier: Programming Language :: Python :: 3
Classifier: Programming Language :: Python :: 3.4
Classifier: Programming Language :: Python :: 3.5
Classifier: Programming Language :: Python :: 3.6
Classifier: Programming Language :: Python :: 3.7
Classifier: Programming Language :: Python :: 3.8
Classifier: Programming Language :: Python :: 3.9
Classifier: Programming Language :: Python :: 3.10
Classifier: Programming Language :: Python :: 3.11
Classifier: Programming Language :: Python :: 3.12
Classifier: Programming Language :: Python :: 3.13
Classifier: License :: OSI Approved :: The Unlicense (Unlicense)
Classifier: Operating System :: OS Independent
Classifier: Development Status :: 5 - Production/Stable
Classifier: Topic :: File Formats
Classifier: Topic :: Multimedia :: Graphics
Classifier: Topic :: Multimedia :: Graphics :: Graphics Conversion
Classifier: Topic :: Software Development :: Libraries :: Python Modules
Classifier: Intended Audience :: Developers
Classifier: Intended Audience :: Education
Classifier: Intended Audience :: Science/Research
Requires-Python: >=3.4
License-File: LICENSE
Dynamic: author
Dynamic: author-email
Dynamic: classifier
Dynamic: description
Dynamic: description-content-type
Dynamic: home-page
Dynamic: keywords
Dynamic: license-file
Dynamic: project-url
Dynamic: requires-python
Dynamic: summary
